modgeosys/__init__.py
modgeosys/graph/__init__.py
modgeosys/graph/cuda/__init__.py
modgeosys/graph/cuda/steiner.py
tests/modgeosys/graph/cuda/conftest.py
modgeosys_cuda_graph_algorithms-0.3.1.dist-info/LICENSE
modgeosys_cuda_graph_algorithms-0.3.1.dist-info/METADATA
modgeosys_cuda_graph_algorithms-0.3.1.dist-info/WHEEL
modgeosys_cuda_graph_algorithms-0.3.1.dist-info/RECORD
